{
    "weather": {
        "atual": 15.2,
        "manha": 15.7,
        "tarde": 21.0,
        "noite": 16.9
    },
    "forecast": {
        "max": 23.5,
        "min": 14.6
    },
    "news": [
        {
            "title": "Uma negociação à procura do ambiente certo",
            "url": "https://www.publico.pthttps://www.publico.pt/2026/04/24/opiniao/editorial/negociacao-procura-ambiente-certo-2172349"
        },
        {
            "title": "Cartas ao director",
            "url": "https://www.publico.pthttps://www.publico.pt/2026/04/24/opiniao/opiniao/cartas-director-2172245"
        },
        {
            "title": "Qual vai ser a saída limpa do Governo na reforma laboral?",
            "url": "https://www.publico.pthttps://www.publico.pt/2026/04/24/politica/noticia/vai-saida-limpa-governo-reforma-laboral-2172375"
        },
        {
            "title": "Sem saber quem paga, não há democracia",
            "url": "https://www.publico.pthttps://www.publico.pt/2026/04/24/opiniao/opiniao/saber-paga-nao-ha-democracia-2172343"
        },
        {
            "title": "A lei laboral das consequências não intencionais",
            "url": "https://www.publico.pthttps://www.publico.pt/2026/04/24/opiniao/opiniao/lei-laboral-consequencias-nao-intencionais-2172353"
        }
    ],
    "finance": [],
    "last_update": "24/04/2026 04:46"
}