{
    "weather": {
        "atual": 16.3,
        "manha": 15.8,
        "tarde": 13.1,
        "noite": 11.8
    },
    "forecast": {
        "max": 18.4,
        "min": 10.6
    },
    "news": [
        {
            "title": "Vender a identidade por meia dúzia de euros: a nova “economia <em>gig</em>” que alimenta a IA",
            "url": "https://www.publico.pthttps://www.publico.pt/2026/04/07/p3/noticia/vender-identidade-meia-duzia-euros-nova-economia-gig-alimenta-ia-2170062"
        },
        {
            "title": "Os novos 9 mandamentos da Associação Americana do Coração para proteger o coração à mesa",
            "url": "https://www.publico.pthttps://www.publico.pt/2026/04/07/impar/noticia/novos-9-mandamentos-associacao-americana-coracao-proteger-coracao-mesa-2170491"
        },
        {
            "title": "Rosalía em Portugal: da <em>Lux æterna</em> à<em> Lux</em> efémera",
            "url": "https://www.publico.pthttps://www.publico.pt/2026/04/07/culturaipsilon/noticia/rosalia-portugal-lux-æterna-lux-efemera-2170397"
        },
        {
            "title": "Os concertos das estrelas: compra morosa, preços cada vez altos, sempre esgotados",
            "url": "https://www.publico.pthttps://www.publico.pt/2026/04/07/culturaipsilon/noticia/concertos-estrelas-compra-morosa-precos-altos-esgotados-2170390"
        },
        {
            "title": "Juntos em Tomar, Seguro e Montenegro querem “soluções” em vez de “arranjar problemas”",
            "url": "https://www.publico.pthttps://www.publico.pt/2026/04/07/politica/noticia/juntos-tomar-seguro-montenegro-querem-solucoes-arranjar-problemas-2170485"
        }
    ],
    "finance": [],
    "last_update": "07/04/2026 19:50"
}