{
    "weather": {
        "atual": 10.1,
        "manha": 11.2,
        "tarde": 13.0,
        "noite": 11.7
    },
    "forecast": {
        "max": 17.1,
        "min": 10.7
    },
    "news": [
        {
            "title": "Contam-se mísseis de ambos os lados, mas são os <em>drones</em> o maior quebra-cabeças",
            "url": "https://www.publico.pthttps://www.publico.pt/2026/03/06/mundo/noticia/contamse-misseis-ambos-lados-sao-drones-maior-quebracabecas-2167126"
        },
        {
            "title": "Parlamento aprova iniciativas do Chega, PAN e Livre para proteger Alagoas Brancas",
            "url": "https://www.publico.pthttps://www.publico.pt/2026/03/06/azul/noticia/parlamento-aprova-iniciativas-chega-pan-livre-proteger-alagoas-brancas-2167132"
        },
        {
            "title": "Governo satisfeito com o fim do impasse das eleições na Universidade de Trás-os-Montes e Alto Douro",
            "url": "https://www.publico.pthttps://www.publico.pt/2026/03/06/sociedade/noticia/governo-satisfeito-fim-impasse-eleicoes-universidade-trasosmontes-alto-douro-2167136"
        },
        {
            "title": "Esquema fraudulento permitiu regularizar em Portugal imigrantes para trabalharem em Espanha",
            "url": "https://www.publico.pthttps://www.publico.pt/2026/03/06/sociedade/noticia/esquema-fraudulento-permitiu-regularizar-portugal-imigrantes-trabalharem-espanha-2167095"
        },
        {
            "title": "A grande fita da violência verbal",
            "url": "https://www.publico.pthttps://www.publico.pt/2026/03/06/desporto/opiniao/fita-violencia-verbal-2166972"
        }
    ],
    "finance": [],
    "last_update": "06/03/2026 19:58"
}