{
    "weather": {
        "atual": 9.9,
        "manha": 11.8,
        "tarde": 14.9,
        "noite": 11.2
    },
    "forecast": {
        "max": 18.7,
        "min": 9.3
    },
    "news": [
        {
            "title": "Directas do PSD reacendem críticas internas e debate sobre o papel de Passos Coelho",
            "url": "https://www.publico.pthttps://www.publico.pt/2026/03/10/politica/noticia/directas-psd-reacendem-criticas-internas-debate-papel-passos-coelho-2167288"
        },
        {
            "title": "As armas apontadas às crianças",
            "url": "https://www.publico.pthttps://www.publico.pt/2026/03/10/p3/cronica/armas-apontadas-criancas-2167394"
        },
        {
            "title": "O Presidente e os imigrantes",
            "url": "https://www.publico.pthttps://www.publico.pt/2026/03/10/publico-brasil/opiniao/presidente-imigrantes-2167357"
        },
        {
            "title": "Nvidia prepara plataforma aberta para criar agentes de inteligência artificial",
            "url": "https://www.publico.pthttps://www.publico.pt/2026/03/10/enter/noticia/nvidia-prepara-plataforma-aberta-criar-agentes-inteligencia-artificial-2167379"
        },
        {
            "title": "Mercadona lucra 26 milhões de euros em Portugal",
            "url": "https://www.publico.pthttps://www.publico.pt/2026/03/10/economia/noticia/mercadona-lucra-26-milhoes-euros-portugal-2167375"
        }
    ],
    "finance": [],
    "last_update": "10/03/2026 11:25"
}