{
    "weather": {
        "atual": 16.9,
        "manha": 16.1,
        "tarde": 22.2,
        "noite": 17.8
    },
    "forecast": {
        "max": 16.6,
        "min": 11.9
    },
    "news": [
        {
            "title": "Juiz que assinou duas distribuições consideradas viciadas escapa a sanções",
            "url": "https://www.publico.pthttps://www.publico.pt/2026/04/10/sociedade/noticia/juiz-assinou-duas-distribuicoes-consideradas-viciadas-escapa-sancoes-2170888"
        },
        {
            "title": "Após semana a ver estragos do mau tempo, Seguro promete manter Governo sob “vigilância”",
            "url": "https://www.publico.pthttps://www.publico.pt/2026/04/10/politica/reportagem/apos-semana-estragos-mau-tempo-seguro-promete-manter-governo-vigilancia-2170863"
        },
        {
            "title": "A mão de Seguro nas leis laborais",
            "url": "https://www.publico.pthttps://www.publico.pt/2026/04/10/opiniao/editorial/mao-seguro-leis-laborais-2170860"
        },
        {
            "title": "O que a ciência nos diz sobre gomas e suplementos alimentares",
            "url": "https://www.publico.pthttps://www.publico.pt/2026/04/10/p3/cronica/ciencia-gomas-suplementos-alimentares-2170093"
        },
        {
            "title": "Entre brinquedos e escombros: as famílias que os ataques israelitas desfizeram em dez minutos",
            "url": "https://www.publico.pthttps://www.publico.pt/2026/04/10/mundo/noticia/brinquedos-escombros-familias-ataques-israelitas-desfizeram-dez-minutos-2170873"
        }
    ],
    "finance": [],
    "last_update": "10/04/2026 21:27"
}