{
    "weather": {
        "atual": 12.8,
        "manha": 14.3,
        "tarde": 21.3,
        "noite": 16.5
    },
    "forecast": {
        "max": 21.0,
        "min": 11.6
    },
    "news": [
        {
            "title": "A resposta do Governo à crise de Ormuz",
            "url": "https://www.publico.pthttps://www.publico.pt/2026/03/16/opiniao/opiniao/resposta-governo-crise-ormuz-2167983"
        },
        {
            "title": "Será o IVA zero a (única) solução para mitigar a subida do preço dos alimentos?",
            "url": "https://www.publico.pthttps://www.publico.pt/2026/03/16/opiniao/opiniao/sera-iva-zero-unica-solucao-mitigar-subida-preco-alimentos-2167795"
        },
        {
            "title": "Porquê?",
            "url": "https://www.publico.pthttps://www.publico.pt/2026/03/16/opiniao/opiniao/2167950"
        },
        {
            "title": "A República das Bainhas",
            "url": "https://www.publico.pthttps://www.publico.pt/2026/03/16/opiniao/opiniao/republica-bainhas-2167939"
        },
        {
            "title": "Co-produzir um novo plano para uma Região Centro resiliente",
            "url": "https://www.publico.pthttps://www.publico.pt/2026/03/16/opiniao/opiniao/coproduzir-novo-plano-regiao-centro-resiliente-2167817"
        }
    ],
    "finance": [],
    "last_update": "16/03/2026 01:19"
}