{
    "weather": {
        "atual": 19.9,
        "manha": 17.2,
        "tarde": 22.6,
        "noite": 17.1
    },
    "forecast": {
        "max": 18.5,
        "min": 15.3
    },
    "news": [
        {
            "title": "Com comunidade brasileira maior, consulado reforça pessoal. CPLP também faz seleção",
            "url": "https://www.publico.pthttps://www.publico.pt/2026/04/28/publico-brasil/noticia/comunidade-brasileira-maior-consulado-reforca-pessoal-cplp-tambem-faz-selecao-2172853"
        },
        {
            "title": "Nove golos em Paris: Bayern assustou, mas PSG reagiu com arte",
            "url": "https://www.publico.pthttps://www.publico.pt/2026/04/28/desporto/noticia/nove-golos-paris-bayern-assustou-psg-reagiu-arte-2172884"
        },
        {
            "title": "Incidentes de segurança informática em Portugal aumentaram 40% em 2025",
            "url": "https://www.publico.pthttps://www.publico.pt/2026/04/28/enter/noticia/incidentes-seguranca-informatica-portugal-aumentaram-40-2025-2172880"
        },
        {
            "title": "Finalmente uma comédia do Irão? Negra... — entrevista com o realizador de <em>Divina Comédia</em>",
            "url": "https://www.publico.pthttps://www.publico.pt/2026/04/28/culturaipsilon/noticia/finalmente-comedia-irao-negra-entrevista-realizador-divina-comedia-2172589"
        },
        {
            "title": "A violência, Trump e uma piada",
            "url": "https://www.publico.pthttps://www.publico.pt/2026/04/28/opiniao/editorial/violencia-trump-piada-2172854"
        }
    ],
    "finance": [],
    "last_update": "28/04/2026 21:55"
}